mrap/__init__.py
mrap/add_input.py
mrap/add_level.py
mrap/add_output.py
mrap/add_software_method.py
mrap/add_target.py
mrap/analytic_instances.py
mrap/list_algorithm_evaluations.py
mrap/scipy_f_oneway.py
mrap/to_jsonld.py
mrap/utils.py
mrap/write_analytic_instance.py
mrap-1.0.1.dist-info/licenses/LICENSE
mrap-1.0.1.dist-info/METADATA
mrap-1.0.1.dist-info/WHEEL
mrap-1.0.1.dist-info/top_level.txt
mrap-1.0.1.dist-info/RECORD
