Metadata-Version: 2.4
Name: mrap
Version: 1.0.1
Summary: Machine-Readable Data Analysis Results with Function Wrappers
Author-email: Olga Lezhnina <olga.lezhnina@tib.eu>, Manuel Prinz <manuel.prinz@tib.eu>, Markus Stocker <markus.stocker@tib.eu>
Maintainer-email: Markus Stocker <markus.stocker@tib.eu>
License: MIT
Project-URL: Repository, https://gitlab.com/TIBHannover/orkg/dtreg-python
Keywords: wrappers,schema,JSON-LD
Classifier: Intended Audience :: Science/Research
Classifier: Topic :: Scientific/Engineering
Classifier: Programming Language :: Python :: 3
Classifier: License :: OSI Approved :: MIT License
Requires-Python: >=3.8
License-File: LICENSE
Requires-Dist: dtreg
Requires-Dist: pandas
Requires-Dist: varname
Dynamic: license-file
